pedroai/__init__.py
pedroai/altair.py
pedroai/download.py
pedroai/io.py
pedroai/iter.py
pedroai/log.py
pedroai/main.py
pedroai/math.py
pedroai/notifications.py
pedroai/plot.py
pedroai/result.py
pedroai/tex.py
pedroai-0.4.1.dist-info/entry_points.txt
pedroai-0.4.1.dist-info/LICENSE
pedroai-0.4.1.dist-info/WHEEL
pedroai-0.4.1.dist-info/METADATA
pedroai-0.4.1.dist-info/RECORD
