Metadata-Version: 2.1
Name: pedroai
Version: 0.4.1
Summary: 
Author: Pedro Rodriguez
Author-email: me@pedro.ai
Requires-Python: >=3.8,<3.12
Classifier: Programming Language :: Python :: 3
Classifier: Programming Language :: Python :: 3.10
Classifier: Programming Language :: Python :: 3.8
Classifier: Programming Language :: Python :: 3.9
Requires-Dist: altair (>=4.2.0,<5.0.0)
Requires-Dist: altair-saver (>=0.5.0,<0.6.0)
Requires-Dist: plotnine (>=0.9,<0.10)
Requires-Dist: pydantic (>=1.9.0,<2.0.0)
Requires-Dist: pysimdjson[dev] (>=5.0.1,<6.0.0)
Requires-Dist: requests (>=2.27.1,<3.0.0)
Requires-Dist: rich (>=12.4.1,<13.0.0)
Requires-Dist: scipy (>=1.7.3,<2.0.0)
Requires-Dist: toml (>=0.10.2,<0.11.0)
Requires-Dist: typer (>=0.6.1,<0.7.0)
